odoo/addons/l10n_ro_account_report_invoice/README.rst
odoo/addons/l10n_ro_account_report_invoice/__init__.py
odoo/addons/l10n_ro_account_report_invoice/__manifest__.py
odoo/addons/l10n_ro_account_report_invoice/init_hook.py
odoo/addons/l10n_ro_account_report_invoice/i18n/l10n_ro_account_report_invoice.pot
odoo/addons/l10n_ro_account_report_invoice/i18n/ro.po
odoo/addons/l10n_ro_account_report_invoice/migrations/14.0.1.1.1/pre-migration.py
odoo/addons/l10n_ro_account_report_invoice/models/__init__.py
odoo/addons/l10n_ro_account_report_invoice/models/account_move.py
odoo/addons/l10n_ro_account_report_invoice/models/res_company.py
odoo/addons/l10n_ro_account_report_invoice/models/res_config_settings.py
odoo/addons/l10n_ro_account_report_invoice/readme/CONTRIBUTORS.rst
odoo/addons/l10n_ro_account_report_invoice/readme/DESCRIPTION.rst
odoo/addons/l10n_ro_account_report_invoice/readme/INSTALL.rst
odoo/addons/l10n_ro_account_report_invoice/static/description/icon.png
odoo/addons/l10n_ro_account_report_invoice/static/description/index.html
odoo/addons/l10n_ro_account_report_invoice/tests/__init__.py
odoo/addons/l10n_ro_account_report_invoice/tests/test_currency_rate.py
odoo/addons/l10n_ro_account_report_invoice/views/account_invoice_view.xml
odoo/addons/l10n_ro_account_report_invoice/views/invoice_report.xml
odoo/addons/l10n_ro_account_report_invoice/views/res_config_settings_view.xml
odoo14_addon_l10n_ro_account_report_invoice-14.0.2.3.0.dist-info/METADATA
odoo14_addon_l10n_ro_account_report_invoice-14.0.2.3.0.dist-info/WHEEL
odoo14_addon_l10n_ro_account_report_invoice-14.0.2.3.0.dist-info/top_level.txt
odoo14_addon_l10n_ro_account_report_invoice-14.0.2.3.0.dist-info/RECORD
